language_data/__init__.py
language_data/build_data.py
language_data/language_lists.py
language_data/name_data.py
language_data/names.py
language_data/population_data.py
language_data/registry_parser.py
language_data/util.py
language_data/data/extra_language_names.csv
language_data/data/language-subtag-registry.txt
language_data/data/languageInfo.xml
language_data/data/override_language_names.csv
language_data/data/supplementalData.xml
language_data/data/trie/ab/name_to_language.marisa
language_data/data/trie/af/name_to_language.marisa
language_data/data/trie/af/name_to_script.marisa
language_data/data/trie/af/name_to_territory.marisa
language_data/data/trie/agq/name_to_language.marisa
language_data/data/trie/agq/name_to_script.marisa
language_data/data/trie/agq/name_to_territory.marisa
language_data/data/trie/ak/name_to_language.marisa
language_data/data/trie/ak/name_to_script.marisa
language_data/data/trie/ak/name_to_territory.marisa
language_data/data/trie/am/name_to_language.marisa
language_data/data/trie/am/name_to_script.marisa
language_data/data/trie/am/name_to_territory.marisa
language_data/data/trie/an/name_to_language.marisa
language_data/data/trie/ang/name_to_language.marisa
language_data/data/trie/ann/name_to_language.marisa
language_data/data/trie/apc/name_to_language.marisa
language_data/data/trie/ar/name_to_language.marisa
language_data/data/trie/ar/name_to_script.marisa
language_data/data/trie/ar/name_to_territory.marisa
language_data/data/trie/arn/name_to_language.marisa
language_data/data/trie/as/name_to_language.marisa
language_data/data/trie/as/name_to_script.marisa
language_data/data/trie/as/name_to_territory.marisa
language_data/data/trie/asa/name_to_language.marisa
language_data/data/trie/asa/name_to_script.marisa
language_data/data/trie/asa/name_to_territory.marisa
language_data/data/trie/ast/name_to_language.marisa
language_data/data/trie/ast/name_to_script.marisa
language_data/data/trie/ast/name_to_territory.marisa
language_data-1.2.0.dist-info/LICENSE
language_data-1.2.0.dist-info/METADATA
language_data-1.2.0.dist-info/WHEEL
language_data-1.2.0.dist-info/top_level.txt
language_data-1.2.0.dist-info/RECORD
