Metadata-Version: 2.1
Name: language_data
Version: 1.2.0
Summary: Supplementary data about languages used by the langcodes module
Author-email: Elia Robyn Speer <rspeer@arborelia.net>
Maintainer-email: Georg Krause <mail@georg-krause.net>
Project-URL: Homepage, https://github.com/georgkrause/language_data
Project-URL: Repository, https://github.com/georgkrause/language_data
Project-URL: Issues, https://github.com/georgkrause/language_data/issues
Classifier: Development Status :: 5 - Production/Stable
Classifier: License :: OSI Approved :: MIT License
Classifier: Programming Language :: Python :: 3
Classifier: Programming Language :: Python :: 3.8
Classifier: Programming Language :: Python :: 3.9
Classifier: Programming Language :: Python :: 3.10
Classifier: Programming Language :: Python :: 3.11
Classifier: Programming Language :: Python :: 3.12
License-File: LICENSE
Requires-Dist: marisa-trie>=0.7.7
Provides-Extra: test
Requires-Dist: pytest; extra == "test"
Requires-Dist: pytest-cov; extra == "test"
Provides-Extra: build
Requires-Dist: build; extra == "build"
Requires-Dist: twine; extra == "build"
